<?xml version="1.0" encoding="utf-8"?>
<clothing-items>
 <clothing>
  <id>
   665307257
  </id>
  <name>
   New Balance Sweater B-8049
  </name>
  <category>
   Sweater
  </category>
  <size>
   S
  </size>
  <color>
   Фиолетовый
  </color>
  <material>
   Лен
  </material>
  <price>
   532844
  </price>
  <rating>
   2.05
  </rating>
  <reviews>
   14660
  </reviews>
  <sporty>
   no
  </sporty>
 </clothing>
 <clothing>
  <id>
   735544722
  </id>
  <name>
   DC Jeans A-9995
  </name>
  <category>
   Jeans
  </category>
  <size>
   XXL
  </size>
  <color>
   Голубой
  </color>
  <material>
   Шелк
  </material>
  <price>
   701494
  </price>
  <rating>
   3.93
  </rating>
  <reviews>
   917010
  </reviews>
  <sporty>
   yes
  </sporty>
 </clothing>
 <clothing>
  <id>
   275354315
  </id>
  <name>
   Nike Socks I-5910
  </name>
  <category>
   Socks
  </category>
  <size>
   L
  </size>
  <color>
   Зеленый
  </color>
  <material>
   Вискоза
  </material>
  <price>
   708097
  </price>
  <rating>
   1.92
  </rating>
  <reviews>
   184706
  </reviews>
  <new>
   +
  </new>
 </clothing>
 <clothing>
  <id>
   614777794
  </id>
  <name>
   Nike Gloves J-4952
  </name>
  <category>
   Gloves
  </category>
  <size>
   S
  </size>
  <color>
   Голубой
  </color>
  <material>
   Кожа
  </material>
  <price>
   185178
  </price>
  <rating>
   4.36
  </rating>
  <reviews>
   475547
  </reviews>
  <exclusive>
   no
  </exclusive>
 </clothing>
 <clothing>
  <id>
   944855648
  </id>
  <name>
   Reebok Jacket R-9690
  </name>
  <category>
   Jacket
  </category>
  <size>
   M
  </size>
  <color>
   Красный
  </color>
  <material>
   Хлопок
  </material>
  <price>
   437477
  </price>
  <rating>
   2.06
  </rating>
  <reviews>
   878959
  </reviews>
  <new>
   +
  </new>
  <sporty>
   yes
  </sporty>
 </clothing>
 <clothing>
  <id>
   521997625
  </id>
  <name>
   Addidas Handbags D-1008
  </name>
  <category>
   Handbags
  </category>
  <size>
   M
  </size>
  <color>
   Желтый
  </color>
  <material>
   Вискоза
  </material>
  <price>
   669435
  </price>
  <rating>
   4.5
  </rating>
  <reviews>
   242359
  </reviews>
  <new>
   +
  </new>
  <sporty>
   no
  </sporty>
 </clothing>
 <clothing>
  <id>
   714488333
  </id>
  <name>
   Fila Jacket R-8060
  </name>
  <category>
   Jacket
  </category>
  <size>
   XL
  </size>
  <color>
   Оранжевый
  </color>
  <material>
   Вискоза
  </material>
  <price>
   462458
  </price>
  <rating>
   3.93
  </rating>
  <reviews>
   940208
  </reviews>
  <new>
   -
  </new>
  <exclusive>
   yes
  </exclusive>
 </clothing>
 <clothing>
  <id>
   417079236
  </id>
  <name>
   Adidas Dress R-3990
  </name>
  <category>
   Dress
  </category>
  <size>
   M
  </size>
  <color>
   Желтый
  </color>
  <material>
   Шерсть
  </material>
  <price>
   815172
  </price>
  <rating>
   3.37
  </rating>
  <reviews>
   271467
  </reviews>
  <sporty>
   no
  </sporty>
 </clothing>
 <clothing>
  <id>
   260919230
  </id>
  <name>
   Reebok Dress L-1047
  </name>
  <category>
   Dress
  </category>
  <size>
   S
  </size>
  <color>
   Оранжевый
  </color>
  <material>
   Кожа
  </material>
  <price>
   571786
  </price>
  <rating>
   2.81
  </rating>
  <reviews>
   640126
  </reviews>
  <new>
   +
  </new>
  <sporty>
   no
  </sporty>
 </clothing>
 <clothing>
  <id>
   532928833
  </id>
  <name>
   Addidas Hat X-2575
  </name>
  <category>
   Hat
  </category>
  <size>
   S
  </size>
  <color>
   Желтый
  </color>
  <material>
   Лен
  </material>
  <price>
   564384
  </price>
  <rating>
   1.2
  </rating>
  <reviews>
   849219
  </reviews>
  <new>
   +
  </new>
  <sporty>
   no
  </sporty>
 </clothing>
 <clothing>
  <id>
   438815676
  </id>
  <name>
   Ellesse Socks Y-7684
  </name>
  <category>
   Socks
  </category>
  <size>
   L
  </size>
  <color>
   Фиолетовый
  </color>
  <material>
   Шерсть
  </material>
  <price>
   173790
  </price>
  <rating>
   1.49
  </rating>
  <reviews>
   386586
  </reviews>
  <new>
   -
  </new>
  <exclusive>
   no
  </exclusive>
 </clothing>
 <clothing>
  <id>
   944467282
  </id>
  <name>
   PleinSport Dress T-3733
  </name>
  <category>
   Dress
  </category>
  <size>
   L
  </size>
  <color>
   Голубой
  </color>
  <material>
   Вискоза
  </material>
  <price>
   877910
  </price>
  <rating>
   3.75
  </rating>
  <reviews>
   958325
  </reviews>
  <new>
   +
  </new>
  <exclusive>
   yes
  </exclusive>
  <sporty>
   no
  </sporty>
 </clothing>
 <clothing>
  <id>
   603863215
  </id>
  <name>
   New Balance Socks U-8298
  </name>
  <category>
   Socks
  </category>
  <size>
   S
  </size>
  <color>
   Фиолетовый
  </color>
  <material>
   Хлопок
  </material>
  <price>
   373536
  </price>
  <rating>
   2.25
  </rating>
  <reviews>
   794837
  </reviews>
  <new>
   -
  </new>
  <exclusive>
   no
  </exclusive>
  <sporty>
   yes
  </sporty>
 </clothing>
 <clothing>
  <id>
   510746395
  </id>
  <name>
   Converse Socks I-9059
  </name>
  <category>
   Socks
  </category>
  <size>
   S
  </size>
  <color>
   Желтый
  </color>
  <material>
   Лен
  </material>
  <price>
   260035
  </price>
  <rating>
   2.06
  </rating>
  <reviews>
   905871
  </reviews>
  <new>
   -
  </new>
  <sporty>
   no
  </sporty>
 </clothing>
 <clothing>
  <id>
   368551668
  </id>
  <name>
   Vans Belts Q-6909
  </name>
  <category>
   Belts
  </category>
  <size>
   XL
  </size>
  <color>
   Синий
  </color>
  <material>
   Полиэстер
  </material>
  <price>
   989321
  </price>
  <rating>
   1.62
  </rating>
  <reviews>
   244514
  </reviews>
  <exclusive>
   no
  </exclusive>
  <sporty>
   no
  </sporty>
 </clothing>
 <clothing>
  <id>
   272105954
  </id>
  <name>
   Fila Belts Z-1767
  </name>
  <category>
   Belts
  </category>
  <size>
   S
  </size>
  <color>
   Желтый
  </color>
  <material>
   Кожа
  </material>
  <price>
   827693
  </price>
  <rating>
   1.17
  </rating>
  <reviews>
   615786
  </reviews>
  <new>
   -
  </new>
  <exclusive>
   no
  </exclusive>
  <sporty>
   yes
  </sporty>
 </clothing>
 <clothing>
  <id>
   516809950
  </id>
  <name>
   Brooks Blouse B-4287
  </name>
  <category>
   Blouse
  </category>
  <size>
   L
  </size>
  <color>
   Оранжевый
  </color>
  <material>
   Вискоза
  </material>
  <price>
   522578
  </price>
  <rating>
   2.77
  </rating>
  <reviews>
   286414
  </reviews>
  <exclusive>
   no
  </exclusive>
 </clothing>
 <clothing>
  <id>
   999433623
  </id>
  <name>
   Lacoste Sweater H-8028
  </name>
  <category>
   Sweater
  </category>
  <size>
   XL
  </size>
  <color>
   Желтый
  </color>
  <material>
   Шерсть
  </material>
  <price>
   940797
  </price>
  <rating>
   2.36
  </rating>
  <reviews>
   22502
  </reviews>
  <new>
   +
  </new>
  <exclusive>
   no
  </exclusive>
  <sporty>
   no
  </sporty>
 </clothing>
 <clothing>
  <id>
   591374705
  </id>
  <name>
   Nike Belts Z-3219
  </name>
  <category>
   Belts
  </category>
  <size>
   L
  </size>
  <color>
   Зеленый
  </color>
  <material>
   Хлопок
  </material>
  <price>
   778566
  </price>
  <rating>
   3.97
  </rating>
  <reviews>
   48496
  </reviews>
  <new>
   -
  </new>
  <sporty>
   no
  </sporty>
 </clothing>
 <clothing>
  <id>
   713444944
  </id>
  <name>
   DC Shoes N-3193
  </name>
  <category>
   Shoes
  </category>
  <size>
   XXL
  </size>
  <color>
   Оранжевый
  </color>
  <material>
   Вискоза
  </material>
  <price>
   985486
  </price>
  <rating>
   5.0
  </rating>
  <reviews>
   163135
  </reviews>
  <new>
   -
  </new>
  <exclusive>
   no
  </exclusive>
 </clothing>
 <clothing>
  <id>
   438781125
  </id>
  <name>
   PleinSport Handbags W-2902
  </name>
  <category>
   Handbags
  </category>
  <size>
   XXL
  </size>
  <color>
   Фиолетовый
  </color>
  <material>
   Шелк
  </material>
  <price>
   433902
  </price>
  <rating>
   4.51
  </rating>
  <reviews>
   961013
  </reviews>
 </clothing>
 <clothing>
  <id>
   140688973
  </id>
  <name>
   Converse Blouse H-7047
  </name>
  <category>
   Blouse
  </category>
  <size>
   L
  </size>
  <color>
   Желтый
  </color>
  <material>
   Вискоза
  </material>
  <price>
   725314
  </price>
  <rating>
   2.49
  </rating>
  <reviews>
   475861
  </reviews>
  <exclusive>
   no
  </exclusive>
 </clothing>
 <clothing>
  <id>
   169777491
  </id>
  <name>
   PleinSport Shoes T-8469
  </name>
  <category>
   Shoes
  </category>
  <size>
   S
  </size>
  <color>
   Красный
  </color>
  <material>
   Шерсть
  </material>
  <price>
   612976
  </price>
  <rating>
   1.62
  </rating>
  <reviews>
   386129
  </reviews>
  <sporty>
   no
  </sporty>
 </clothing>
 <clothing>
  <id>
   258250261
  </id>
  <name>
   Addidas Belts L-3484
  </name>
  <category>
   Belts
  </category>
  <size>
   S
  </size>
  <color>
   Желтый
  </color>
  <material>
   Шерсть
  </material>
  <price>
   135059
  </price>
  <rating>
   3.74
  </rating>
  <reviews>
   192622
  </reviews>
  <exclusive>
   no
  </exclusive>
 </clothing>
 <clothing>
  <id>
   761740616
  </id>
  <name>
   Asics Sweater I-8836
  </name>
  <category>
   Sweater
  </category>
  <size>
   M
  </size>
  <color>
   Зеленый
  </color>
  <material>
   Нейлон
  </material>
  <price>
   386102
  </price>
  <rating>
   3.44
  </rating>
  <reviews>
   71511
  </reviews>
  <sporty>
   yes
  </sporty>
 </clothing>
 <clothing>
  <id>
   397253441
  </id>
  <name>
   New Balance Dress Y-5674
  </name>
  <category>
   Dress
  </category>
  <size>
   M
  </size>
  <color>
   Зеленый
  </color>
  <material>
   Шерсть
  </material>
  <price>
   624023
  </price>
  <rating>
   2.55
  </rating>
  <reviews>
   810208
  </reviews>
 </clothing>
 <clothing>
  <id>
   765927078
  </id>
  <name>
   Addidas Belts W-4632
  </name>
  <category>
   Belts
  </category>
  <size>
   XXL
  </size>
  <color>
   Оранжевый
  </color>
  <material>
   Хлопок
  </material>
  <price>
   405234
  </price>
  <rating>
   2.94
  </rating>
  <reviews>
   196046
  </reviews>
  <new>
   -
  </new>
  <exclusive>
   no
  </exclusive>
 </clothing>
 <clothing>
  <id>
   715339897
  </id>
  <name>
   Under Armour Sweater N-6440
  </name>
  <category>
   Sweater
  </category>
  <size>
   XL
  </size>
  <color>
   Оранжевый
  </color>
  <material>
   Хлопок
  </material>
  <price>
   970877
  </price>
  <rating>
   4.9
  </rating>
  <reviews>
   238698
  </reviews>
  <new>
   +
  </new>
 </clothing>
 <clothing>
  <id>
   158294281
  </id>
  <name>
   Reebok Jacket N-9150
  </name>
  <category>
   Jacket
  </category>
  <size>
   S
  </size>
  <color>
   Оранжевый
  </color>
  <material>
   Хлопок
  </material>
  <price>
   612125
  </price>
  <rating>
   2.63
  </rating>
  <reviews>
   137293
  </reviews>
  <new>
   +
  </new>
  <exclusive>
   yes
  </exclusive>
 </clothing>
 <clothing>
  <id>
   820335230
  </id>
  <name>
   Asics Jacket S-7606
  </name>
  <category>
   Jacket
  </category>
  <size>
   XL
  </size>
  <color>
   Красный
  </color>
  <material>
   Лен
  </material>
  <price>
   997746
  </price>
  <rating>
   2.02
  </rating>
  <reviews>
   950186
  </reviews>
  <exclusive>
   no
  </exclusive>
 </clothing>
</clothing-items>
