<?xml version="1.0" encoding="utf-8"?>
<clothing-items>
 <clothing>
  <id>
   968941487
  </id>
  <name>
   Addidas Jeans N-4699
  </name>
  <category>
   Jeans
  </category>
  <size>
   S
  </size>
  <color>
   Фиолетовый
  </color>
  <material>
   Нейлон
  </material>
  <price>
   467878
  </price>
  <rating>
   4.61
  </rating>
  <reviews>
   434598
  </reviews>
  <new>
   -
  </new>
 </clothing>
 <clothing>
  <id>
   654904429
  </id>
  <name>
   Converse Dress Z-4454
  </name>
  <category>
   Dress
  </category>
  <size>
   L
  </size>
  <color>
   Красный
  </color>
  <material>
   Хлопок
  </material>
  <price>
   333785
  </price>
  <rating>
   1.01
  </rating>
  <reviews>
   975251
  </reviews>
  <new>
   +
  </new>
  <sporty>
   no
  </sporty>
 </clothing>
 <clothing>
  <id>
   817633848
  </id>
  <name>
   Puma Belts S-1218
  </name>
  <category>
   Belts
  </category>
  <size>
   M
  </size>
  <color>
   Красный
  </color>
  <material>
   Вискоза
  </material>
  <price>
   466963
  </price>
  <rating>
   1.52
  </rating>
  <reviews>
   268257
  </reviews>
  <new>
   +
  </new>
 </clothing>
 <clothing>
  <id>
   439003795
  </id>
  <name>
   Under Armour Dress A-3412
  </name>
  <category>
   Dress
  </category>
  <size>
   XXL
  </size>
  <color>
   Желтый
  </color>
  <material>
   Кожа
  </material>
  <price>
   708561
  </price>
  <rating>
   1.69
  </rating>
  <reviews>
   758387
  </reviews>
  <exclusive>
   no
  </exclusive>
  <sporty>
   yes
  </sporty>
 </clothing>
 <clothing>
  <id>
   399184432
  </id>
  <name>
   New Balance T-shirt I-2835
  </name>
  <category>
   T-shirt
  </category>
  <size>
   L
  </size>
  <color>
   Желтый
  </color>
  <material>
   Хлопок
  </material>
  <price>
   304566
  </price>
  <rating>
   4.66
  </rating>
  <reviews>
   121325
  </reviews>
  <new>
   -
  </new>
  <exclusive>
   no
  </exclusive>
  <sporty>
   no
  </sporty>
 </clothing>
 <clothing>
  <id>
   872009630
  </id>
  <name>
   Nike Sweater Z-8809
  </name>
  <category>
   Sweater
  </category>
  <size>
   S
  </size>
  <color>
   Красный
  </color>
  <material>
   Нейлон
  </material>
  <price>
   373249
  </price>
  <rating>
   1.14
  </rating>
  <reviews>
   531117
  </reviews>
  <new>
   -
  </new>
  <sporty>
   no
  </sporty>
 </clothing>
 <clothing>
  <id>
   978332968
  </id>
  <name>
   New Balance Pants Z-5381
  </name>
  <category>
   Pants
  </category>
  <size>
   S
  </size>
  <color>
   Желтый
  </color>
  <material>
   Шелк
  </material>
  <price>
   330296
  </price>
  <rating>
   3.21
  </rating>
  <reviews>
   686023
  </reviews>
  <new>
   -
  </new>
 </clothing>
 <clothing>
  <id>
   431750746
  </id>
  <name>
   Under Armour Socks Q-8277
  </name>
  <category>
   Socks
  </category>
  <size>
   L
  </size>
  <color>
   Оранжевый
  </color>
  <material>
   Вискоза
  </material>
  <price>
   279230
  </price>
  <rating>
   1.87
  </rating>
  <reviews>
   639772
  </reviews>
  <new>
   +
  </new>
  <exclusive>
   no
  </exclusive>
 </clothing>
 <clothing>
  <id>
   197230531
  </id>
  <name>
   Ellesse Shirt R-4318
  </name>
  <category>
   Shirt
  </category>
  <size>
   M
  </size>
  <color>
   Голубой
  </color>
  <material>
   Шелк
  </material>
  <price>
   304726
  </price>
  <rating>
   4.09
  </rating>
  <reviews>
   378687
  </reviews>
  <new>
   +
  </new>
  <exclusive>
   no
  </exclusive>
  <sporty>
   yes
  </sporty>
 </clothing>
 <clothing>
  <id>
   336474770
  </id>
  <name>
   Asics Socks Z-2593
  </name>
  <category>
   Socks
  </category>
  <size>
   L
  </size>
  <color>
   Голубой
  </color>
  <material>
   Лен
  </material>
  <price>
   847633
  </price>
  <rating>
   1.22
  </rating>
  <reviews>
   684405
  </reviews>
  <exclusive>
   no
  </exclusive>
  <sporty>
   yes
  </sporty>
 </clothing>
 <clothing>
  <id>
   819665759
  </id>
  <name>
   Converse Blouse C-6123
  </name>
  <category>
   Blouse
  </category>
  <size>
   M
  </size>
  <color>
   Зеленый
  </color>
  <material>
   Шерсть
  </material>
  <price>
   879038
  </price>
  <rating>
   3.21
  </rating>
  <reviews>
   387521
  </reviews>
  <new>
   +
  </new>
 </clothing>
 <clothing>
  <id>
   635567037
  </id>
  <name>
   Brooks Belts V-5598
  </name>
  <category>
   Belts
  </category>
  <size>
   XL
  </size>
  <color>
   Оранжевый
  </color>
  <material>
   Нейлон
  </material>
  <price>
   351813
  </price>
  <rating>
   3.79
  </rating>
  <reviews>
   661261
  </reviews>
  <new>
   -
  </new>
  <exclusive>
   no
  </exclusive>
  <sporty>
   no
  </sporty>
 </clothing>
 <clothing>
  <id>
   358362456
  </id>
  <name>
   Converse Shoes F-8885
  </name>
  <category>
   Shoes
  </category>
  <size>
   M
  </size>
  <color>
   Фиолетовый
  </color>
  <material>
   Кожа
  </material>
  <price>
   328533
  </price>
  <rating>
   4.51
  </rating>
  <reviews>
   927090
  </reviews>
  <sporty>
   yes
  </sporty>
 </clothing>
 <clothing>
  <id>
   368573828
  </id>
  <name>
   Fila Shoes B-9261
  </name>
  <category>
   Shoes
  </category>
  <size>
   XXL
  </size>
  <color>
   Зеленый
  </color>
  <material>
   Шелк
  </material>
  <price>
   132059
  </price>
  <rating>
   4.4
  </rating>
  <reviews>
   565418
  </reviews>
  <new>
   +
  </new>
  <exclusive>
   yes
  </exclusive>
 </clothing>
 <clothing>
  <id>
   658968948
  </id>
  <name>
   Ellesse Hat Y-4324
  </name>
  <category>
   Hat
  </category>
  <size>
   XL
  </size>
  <color>
   Голубой
  </color>
  <material>
   Полиэстер
  </material>
  <price>
   382576
  </price>
  <rating>
   3.6
  </rating>
  <reviews>
   159531
  </reviews>
  <sporty>
   no
  </sporty>
 </clothing>
 <clothing>
  <id>
   114528874
  </id>
  <name>
   DC Shirt A-5645
  </name>
  <category>
   Shirt
  </category>
  <size>
   L
  </size>
  <color>
   Оранжевый
  </color>
  <material>
   Вискоза
  </material>
  <price>
   983843
  </price>
  <rating>
   3.02
  </rating>
  <reviews>
   438900
  </reviews>
  <exclusive>
   yes
  </exclusive>
  <sporty>
   yes
  </sporty>
 </clothing>
 <clothing>
  <id>
   359161521
  </id>
  <name>
   Under Armour Belts Y-3367
  </name>
  <category>
   Belts
  </category>
  <size>
   S
  </size>
  <color>
   Желтый
  </color>
  <material>
   Шелк
  </material>
  <price>
   939762
  </price>
  <rating>
   1.58
  </rating>
  <reviews>
   611596
  </reviews>
  <new>
   -
  </new>
  <sporty>
   no
  </sporty>
 </clothing>
 <clothing>
  <id>
   253427811
  </id>
  <name>
   Fila Hat H-2275
  </name>
  <category>
   Hat
  </category>
  <size>
   L
  </size>
  <color>
   Оранжевый
  </color>
  <material>
   Вискоза
  </material>
  <price>
   370299
  </price>
  <rating>
   4.36
  </rating>
  <reviews>
   328373
  </reviews>
 </clothing>
 <clothing>
  <id>
   534162689
  </id>
  <name>
   Reebok Umbrellas B-7487
  </name>
  <category>
   Umbrellas
  </category>
  <size>
   L
  </size>
  <color>
   Зеленый
  </color>
  <material>
   Хлопок
  </material>
  <price>
   285648
  </price>
  <rating>
   4.59
  </rating>
  <reviews>
   507306
  </reviews>
  <exclusive>
   no
  </exclusive>
 </clothing>
 <clothing>
  <id>
   422158002
  </id>
  <name>
   Brooks Umbrellas G-5190
  </name>
  <category>
   Umbrellas
  </category>
  <size>
   XXL
  </size>
  <color>
   Фиолетовый
  </color>
  <material>
   Лен
  </material>
  <price>
   255522
  </price>
  <rating>
   2.06
  </rating>
  <reviews>
   298187
  </reviews>
  <exclusive>
   no
  </exclusive>
  <sporty>
   no
  </sporty>
 </clothing>
 <clothing>
  <id>
   111865814
  </id>
  <name>
   Puma Shoes O-3939
  </name>
  <category>
   Shoes
  </category>
  <size>
   XXL
  </size>
  <color>
   Оранжевый
  </color>
  <material>
   Шерсть
  </material>
  <price>
   250182
  </price>
  <rating>
   1.07
  </rating>
  <reviews>
   438002
  </reviews>
  <new>
   +
  </new>
  <exclusive>
   no
  </exclusive>
  <sporty>
   no
  </sporty>
 </clothing>
 <clothing>
  <id>
   695885429
  </id>
  <name>
   Converse Dress B-7880
  </name>
  <category>
   Dress
  </category>
  <size>
   M
  </size>
  <color>
   Зеленый
  </color>
  <material>
   Нейлон
  </material>
  <price>
   463267
  </price>
  <rating>
   1.28
  </rating>
  <reviews>
   108731
  </reviews>
  <new>
   -
  </new>
 </clothing>
 <clothing>
  <id>
   683292680
  </id>
  <name>
   Adidas T-shirt H-6352
  </name>
  <category>
   T-shirt
  </category>
  <size>
   XXL
  </size>
  <color>
   Фиолетовый
  </color>
  <material>
   Шерсть
  </material>
  <price>
   244020
  </price>
  <rating>
   4.86
  </rating>
  <reviews>
   512183
  </reviews>
  <new>
   +
  </new>
  <sporty>
   yes
  </sporty>
 </clothing>
 <clothing>
  <id>
   138138076
  </id>
  <name>
   Ellesse Belts E-7148
  </name>
  <category>
   Belts
  </category>
  <size>
   XL
  </size>
  <color>
   Голубой
  </color>
  <material>
   Лен
  </material>
  <price>
   429122
  </price>
  <rating>
   4.67
  </rating>
  <reviews>
   767489
  </reviews>
  <new>
   +
  </new>
 </clothing>
 <clothing>
  <id>
   147870312
  </id>
  <name>
   Lacoste Skirt E-8646
  </name>
  <category>
   Skirt
  </category>
  <size>
   XXL
  </size>
  <color>
   Голубой
  </color>
  <material>
   Шелк
  </material>
  <price>
   734601
  </price>
  <rating>
   2.5
  </rating>
  <reviews>
   676777
  </reviews>
  <new>
   -
  </new>
  <sporty>
   no
  </sporty>
 </clothing>
 <clothing>
  <id>
   357615658
  </id>
  <name>
   Reebok Pants D-7381
  </name>
  <category>
   Pants
  </category>
  <size>
   M
  </size>
  <color>
   Голубой
  </color>
  <material>
   Шелк
  </material>
  <price>
   852128
  </price>
  <rating>
   2.06
  </rating>
  <reviews>
   688627
  </reviews>
  <exclusive>
   yes
  </exclusive>
  <sporty>
   yes
  </sporty>
 </clothing>
 <clothing>
  <id>
   545391443
  </id>
  <name>
   Adidas Hat U-1930
  </name>
  <category>
   Hat
  </category>
  <size>
   M
  </size>
  <color>
   Желтый
  </color>
  <material>
   Шелк
  </material>
  <price>
   386155
  </price>
  <rating>
   2.54
  </rating>
  <reviews>
   156009
  </reviews>
  <new>
   +
  </new>
  <sporty>
   no
  </sporty>
 </clothing>
 <clothing>
  <id>
   346187933
  </id>
  <name>
   Vans Blouse Y-4123
  </name>
  <category>
   Blouse
  </category>
  <size>
   M
  </size>
  <color>
   Голубой
  </color>
  <material>
   Нейлон
  </material>
  <price>
   214800
  </price>
  <rating>
   4.96
  </rating>
  <reviews>
   570745
  </reviews>
  <new>
   -
  </new>
  <exclusive>
   no
  </exclusive>
 </clothing>
 <clothing>
  <id>
   293897361
  </id>
  <name>
   Under Armour Jacket O-9908
  </name>
  <category>
   Jacket
  </category>
  <size>
   M
  </size>
  <color>
   Оранжевый
  </color>
  <material>
   Полиэстер
  </material>
  <price>
   292864
  </price>
  <rating>
   1.84
  </rating>
  <reviews>
   208241
  </reviews>
  <new>
   -
  </new>
  <exclusive>
   yes
  </exclusive>
  <sporty>
   yes
  </sporty>
 </clothing>
 <clothing>
  <id>
   621818801
  </id>
  <name>
   Asics T-shirt A-4138
  </name>
  <category>
   T-shirt
  </category>
  <size>
   L
  </size>
  <color>
   Фиолетовый
  </color>
  <material>
   Полиэстер
  </material>
  <price>
   811645
  </price>
  <rating>
   3.84
  </rating>
  <reviews>
   612092
  </reviews>
  <sporty>
   no
  </sporty>
 </clothing>
 <clothing>
  <id>
   105387706
  </id>
  <name>
   Lacoste Shoes J-3975
  </name>
  <category>
   Shoes
  </category>
  <size>
   S
  </size>
  <color>
   Желтый
  </color>
  <material>
   Шелк
  </material>
  <price>
   873657
  </price>
  <rating>
   1.99
  </rating>
  <reviews>
   924559
  </reviews>
  <new>
   -
  </new>
  <exclusive>
   no
  </exclusive>
  <sporty>
   no
  </sporty>
 </clothing>
 <clothing>
  <id>
   606520550
  </id>
  <name>
   Fila Handbags T-3623
  </name>
  <category>
   Handbags
  </category>
  <size>
   XL
  </size>
  <color>
   Желтый
  </color>
  <material>
   Хлопок
  </material>
  <price>
   968385
  </price>
  <rating>
   1.35
  </rating>
  <reviews>
   982064
  </reviews>
  <new>
   -
  </new>
  <exclusive>
   no
  </exclusive>
  <sporty>
   no
  </sporty>
 </clothing>
 <clothing>
  <id>
   264153178
  </id>
  <name>
   Ellesse Blouse V-6506
  </name>
  <category>
   Blouse
  </category>
  <size>
   S
  </size>
  <color>
   Голубой
  </color>
  <material>
   Кожа
  </material>
  <price>
   871522
  </price>
  <rating>
   3.61
  </rating>
  <reviews>
   317196
  </reviews>
  <new>
   -
  </new>
  <exclusive>
   yes
  </exclusive>
  <sporty>
   no
  </sporty>
 </clothing>
 <clothing>
  <id>
   937022063
  </id>
  <name>
   Vans Jeans V-1616
  </name>
  <category>
   Jeans
  </category>
  <size>
   L
  </size>
  <color>
   Красный
  </color>
  <material>
   Шелк
  </material>
  <price>
   866744
  </price>
  <rating>
   4.97
  </rating>
  <reviews>
   948050
  </reviews>
  <new>
   -
  </new>
  <exclusive>
   no
  </exclusive>
  <sporty>
   no
  </sporty>
 </clothing>
 <clothing>
  <id>
   308170589
  </id>
  <name>
   Asics Sweater N-5942
  </name>
  <category>
   Sweater
  </category>
  <size>
   L
  </size>
  <color>
   Оранжевый
  </color>
  <material>
   Нейлон
  </material>
  <price>
   111319
  </price>
  <rating>
   3.84
  </rating>
  <reviews>
   914064
  </reviews>
 </clothing>
 <clothing>
  <id>
   812800651
  </id>
  <name>
   Puma Jacket R-3243
  </name>
  <category>
   Jacket
  </category>
  <size>
   L
  </size>
  <color>
   Фиолетовый
  </color>
  <material>
   Кожа
  </material>
  <price>
   642542
  </price>
  <rating>
   3.47
  </rating>
  <reviews>
   245404
  </reviews>
  <sporty>
   no
  </sporty>
 </clothing>
 <clothing>
  <id>
   385583093
  </id>
  <name>
   Under Armour Hat V-2710
  </name>
  <category>
   Hat
  </category>
  <size>
   XXL
  </size>
  <color>
   Красный
  </color>
  <material>
   Вискоза
  </material>
  <price>
   956509
  </price>
  <rating>
   4.5
  </rating>
  <reviews>
   136168
  </reviews>
  <exclusive>
   no
  </exclusive>
  <sporty>
   yes
  </sporty>
 </clothing>
 <clothing>
  <id>
   974524111
  </id>
  <name>
   Under Armour Jeans B-8358
  </name>
  <category>
   Jeans
  </category>
  <size>
   S
  </size>
  <color>
   Фиолетовый
  </color>
  <material>
   Вискоза
  </material>
  <price>
   955523
  </price>
  <rating>
   4.75
  </rating>
  <reviews>
   44567
  </reviews>
  <exclusive>
   yes
  </exclusive>
 </clothing>
 <clothing>
  <id>
   392135331
  </id>
  <name>
   Addidas Gloves P-7379
  </name>
  <category>
   Gloves
  </category>
  <size>
   S
  </size>
  <color>
   Зеленый
  </color>
  <material>
   Вискоза
  </material>
  <price>
   536189
  </price>
  <rating>
   2.06
  </rating>
  <reviews>
   514208
  </reviews>
  <new>
   -
  </new>
  <exclusive>
   no
  </exclusive>
 </clothing>
 <clothing>
  <id>
   736883595
  </id>
  <name>
   Asics Sweater Q-3740
  </name>
  <category>
   Sweater
  </category>
  <size>
   S
  </size>
  <color>
   Фиолетовый
  </color>
  <material>
   Шерсть
  </material>
  <price>
   249485
  </price>
  <rating>
   3.64
  </rating>
  <reviews>
   844725
  </reviews>
  <new>
   +
  </new>
 </clothing>
 <clothing>
  <id>
   164841071
  </id>
  <name>
   DC Shirt I-5497
  </name>
  <category>
   Shirt
  </category>
  <size>
   XXL
  </size>
  <color>
   Желтый
  </color>
  <material>
   Полиэстер
  </material>
  <price>
   812712
  </price>
  <rating>
   3.68
  </rating>
  <reviews>
   87834
  </reviews>
  <new>
   -
  </new>
  <exclusive>
   no
  </exclusive>
  <sporty>
   no
  </sporty>
 </clothing>
</clothing-items>
